raysql-0.5.0.dist-info/METADATA
raysql-0.5.0.dist-info/WHEEL
raysql-0.5.0.dist-info/license_files/LICENSE
raysql-0.5.0.dist-info/license_files/NOTICE
raysql/tests/test_context.py
raysql/ray_utils.py
raysql/main.py
raysql/__init__.py
raysql/context.py
raysql/_raysql_internal.abi3.so
raysql-0.5.0.dist-info/RECORD
