Metadata-Version: 2.1
Name: raysql
Version: 0.5.0
Classifier: Programming Language :: Rust
Classifier: Programming Language :: Python :: Implementation :: CPython
Classifier: Programming Language :: Python :: Implementation :: PyPy
License-File: LICENSE
License-File: NOTICE
Summary: RaySQL: DataFusion on Ray
Home-Page: https://github.com/andygrove/ray-sql
Author: Andy Grove <andygrove73@gmail.com>
Author-email: Andy Grove <andygrove73@gmail.com>
License: Apache-2.0
Requires-Python: >=3.7
Project-URL: Source Code, https://github.com/andygrove/ray-sql
